MANIFEST.in
README.txt
setup.py
cs/__init__.py
cs.portlet.aemet.egg-info/PKG-INFO
cs.portlet.aemet.egg-info/SOURCES.txt
cs.portlet.aemet.egg-info/dependency_links.txt
cs.portlet.aemet.egg-info/entry_points.txt
cs.portlet.aemet.egg-info/namespace_packages.txt
cs.portlet.aemet.egg-info/not-zip-safe
cs.portlet.aemet.egg-info/requires.txt
cs.portlet.aemet.egg-info/top_level.txt
cs/portlet/__init__.py
cs/portlet/aemet/__init__.py
cs/portlet/aemet/aemetparser.py
cs/portlet/aemet/aemetportlet.pt
cs/portlet/aemet/aemetportlet.py
cs/portlet/aemet/configure.zcml
cs/portlet/aemet/rebuild_i18n.sh
cs/portlet/aemet/locales/cs.portlet.aemet-manual.pot
cs/portlet/aemet/locales/cs.portlet.aemet.pot
cs/portlet/aemet/locales/es/LC_MESSAGES/cs.portlet.aemet.po
cs/portlet/aemet/locales/eu/LC_MESSAGES/cs.portlet.aemet.po
cs/portlet/aemet/profiles/default/metadata.xml
cs/portlet/aemet/profiles/default/portlets.xml
cs/portlet/aemet/tests/__init__.py
cs/portlet/aemet/tests/base.py
cs/portlet/aemet/tests/test_portlet.py
docs/HISTORY.txt
docs/INSTALL.txt
docs/LICENSE.GPL
docs/LICENSE.txt