Metadata-Version: 1.1
Name: cs.portlet.aemet
Version: 1.4.1
Summary: A portlet to show the weather via AEMET
Home-page: https://github.com/codesyntax/cs.portlet.aemet
Author: Mikel Larreategi
Author-email: mlarreategi@codesyntax.com
License: GPL
Keywords: weather portlet plone aemet
Platform: UNKNOWN
Classifier: Framework :: Plone
Classifier: Framework :: Plone :: 4.0
Classifier: Framework :: Plone :: 4.1
Classifier: Framework :: Plone :: 4.2
Classifier: Framework :: Plone :: 4.3
Classifier: Programming Language :: Python
